{
    "attacker_000": [
        [
            1,
            {
                "accuracy": 0.998395,
                "precision": 0.9985716791540331,
                "recall": 0.9998193550976988,
                "f1": 0.9991951276387151,
                "mcc": 0.7438407562785343,
                "missrate": 0.00018064490230121534,
                "fallout": 0.39915966386554624,
                "loss": 0.015136796981096268
            }
        ],
        [
            2,
            {
                "accuracy": 0.9987,
                "precision": 0.9991072413758514,
                "recall": 0.9995885310558694,
                "f1": 0.9993478282681328,
                "mcc": 0.8062667672869933,
                "missrate": 0.00041146894413054605,
                "fallout": 0.24929971988795518,
                "loss": 0.014163291081786156
            }
        ],
        [
            3,
            {
                "accuracy": 0.99876,
                "precision": 0.9993376885329801,
                "recall": 0.9994179219814738,
                "f1": 0.9993778036468735,
                "mcc": 0.8237937553388794,
                "missrate": 0.0005820780185261383,
                "fallout": 0.18487394957983194,
                "loss": 0.010883311741054058
            }
        ],
        [
            4,
            {
                "accuracy": 0.99869,
                "precision": 0.9993326308394802,
                "recall": 0.9993526891000873,
                "f1": 0.9993426598691342,
                "mcc": 0.8153571408161199,
                "missrate": 0.0006473108999126883,
                "fallout": 0.18627450980392157,
                "loss": 0.008461486548185349
            }
        ],
        [
            5,
            {
                "accuracy": 0.99869,
                "precision": 0.9992925451316067,
                "recall": 0.9993928324117098,
                "f1": 0.9993426862556198,
                "mcc": 0.8133459127414695,
                "missrate": 0.000607167588290196,
                "fallout": 0.19747899159663865,
                "loss": 0.0076281181536614895
            }
        ],
        [
            6,
            {
                "accuracy": 0.998665,
                "precision": 0.9993025484578293,
                "recall": 0.9993577070140401,
                "f1": 0.9993301269748083,
                "mcc": 0.81092852345053,
                "missrate": 0.0006422929859598767,
                "fallout": 0.19467787114845939,
                "loss": 0.0089602991938591
            }
        ],
        [
            7,
            {
                "accuracy": 0.99865,
                "precision": 0.9993025379589953,
                "recall": 0.9993426532721816,
                "f1": 0.9993225952130061,
                "mcc": 0.8091947052973801,
                "missrate": 0.0006573467278183113,
                "fallout": 0.19467787114845939,
                "loss": 0.008232737891376019
            }
        ],
        [
            8,
            {
                "accuracy": 0.99871,
                "precision": 0.9993376552997612,
                "recall": 0.9993677428419457,
                "f1": 0.9993526988443918,
                "mcc": 0.8179254442632327,
                "missrate": 0.0006322571580542537,
                "fallout": 0.18487394957983194,
                "loss": 0.008197701536118984
            }
        ],
        [
            9,
            {
                "accuracy": 0.998805,
                "precision": 0.9993377184400258,
                "recall": 0.9994630832070491,
                "f1": 0.999400396892099,
                "mcc": 0.8291839142701373,
                "missrate": 0.0005369167929508345,
                "fallout": 0.18487394957983194,
                "loss": 0.007919574156403542
            }
        ],
        [
            10,
            {
                "accuracy": 0.99878,
                "precision": 0.9993377018253339,
                "recall": 0.9994379936372851,
                "f1": 0.9993878452151573,
                "mcc": 0.826176457095315,
                "missrate": 0.0005620063627148922,
                "fallout": 0.18487394957983194,
                "loss": 0.00890086404979229,
                "attack_stats": [
                    {
                        "attack": "DDoS",
                        "count": 97025,
                        "correct": 97001,
                        "missed": 24,
                        "percentage": "99.98%"
                    },
                    {
                        "attack": "DoS",
                        "count": 88458,
                        "correct": 88438,
                        "missed": 20,
                        "percentage": "99.98%"
                    },
                    {
                        "attack": "Reconnaissance",
                        "count": 13794,
                        "correct": 13726,
                        "missed": 68,
                        "percentage": "99.51%"
                    },
                    {
                        "attack": "Theft",
                        "count": 9,
                        "correct": 9,
                        "missed": 0,
                        "percentage": "100.00%"
                    }
                ]
            }
        ]
    ],
    "client_000": [
        [
            1,
            {
                "accuracy": 0.998395,
                "precision": 0.9985716791540331,
                "recall": 0.9998193550976988,
                "f1": 0.9991951276387151,
                "mcc": 0.7438407562785343,
                "missrate": 0.00018064490230121534,
                "fallout": 0.39915966386554624,
                "loss": 0.015136796981096268
            }
        ],
        [
            2,
            {
                "accuracy": 0.9987,
                "precision": 0.9991072413758514,
                "recall": 0.9995885310558694,
                "f1": 0.9993478282681328,
                "mcc": 0.8062667672869933,
                "missrate": 0.00041146894413054605,
                "fallout": 0.24929971988795518,
                "loss": 0.014163291081786156
            }
        ],
        [
            3,
            {
                "accuracy": 0.99876,
                "precision": 0.9993376885329801,
                "recall": 0.9994179219814738,
                "f1": 0.9993778036468735,
                "mcc": 0.8237937553388794,
                "missrate": 0.0005820780185261383,
                "fallout": 0.18487394957983194,
                "loss": 0.010883311741054058
            }
        ],
        [
            4,
            {
                "accuracy": 0.99869,
                "precision": 0.9993326308394802,
                "recall": 0.9993526891000873,
                "f1": 0.9993426598691342,
                "mcc": 0.8153571408161199,
                "missrate": 0.0006473108999126883,
                "fallout": 0.18627450980392157,
                "loss": 0.008461486548185349
            }
        ],
        [
            5,
            {
                "accuracy": 0.99869,
                "precision": 0.9992925451316067,
                "recall": 0.9993928324117098,
                "f1": 0.9993426862556198,
                "mcc": 0.8133459127414695,
                "missrate": 0.000607167588290196,
                "fallout": 0.19747899159663865,
                "loss": 0.0076281181536614895
            }
        ],
        [
            6,
            {
                "accuracy": 0.998665,
                "precision": 0.9993025484578293,
                "recall": 0.9993577070140401,
                "f1": 0.9993301269748083,
                "mcc": 0.81092852345053,
                "missrate": 0.0006422929859598767,
                "fallout": 0.19467787114845939,
                "loss": 0.0089602991938591
            }
        ],
        [
            7,
            {
                "accuracy": 0.99865,
                "precision": 0.9993025379589953,
                "recall": 0.9993426532721816,
                "f1": 0.9993225952130061,
                "mcc": 0.8091947052973801,
                "missrate": 0.0006573467278183113,
                "fallout": 0.19467787114845939,
                "loss": 0.008232737891376019
            }
        ],
        [
            8,
            {
                "accuracy": 0.99871,
                "precision": 0.9993376552997612,
                "recall": 0.9993677428419457,
                "f1": 0.9993526988443918,
                "mcc": 0.8179254442632327,
                "missrate": 0.0006322571580542537,
                "fallout": 0.18487394957983194,
                "loss": 0.008197701536118984
            }
        ],
        [
            9,
            {
                "accuracy": 0.998805,
                "precision": 0.9993377184400258,
                "recall": 0.9994630832070491,
                "f1": 0.999400396892099,
                "mcc": 0.8291839142701373,
                "missrate": 0.0005369167929508345,
                "fallout": 0.18487394957983194,
                "loss": 0.007919574156403542
            }
        ],
        [
            10,
            {
                "accuracy": 0.99878,
                "precision": 0.9993377018253339,
                "recall": 0.9994379936372851,
                "f1": 0.9993878452151573,
                "mcc": 0.826176457095315,
                "missrate": 0.0005620063627148922,
                "fallout": 0.18487394957983194,
                "loss": 0.00890086404979229,
                "attack_stats": [
                    {
                        "attack": "DDoS",
                        "count": 97025,
                        "correct": 97001,
                        "missed": 24,
                        "percentage": "99.98%"
                    },
                    {
                        "attack": "DoS",
                        "count": 88458,
                        "correct": 88438,
                        "missed": 20,
                        "percentage": "99.98%"
                    },
                    {
                        "attack": "Reconnaissance",
                        "count": 13794,
                        "correct": 13726,
                        "missed": 68,
                        "percentage": "99.51%"
                    },
                    {
                        "attack": "Theft",
                        "count": 9,
                        "correct": 9,
                        "missed": 0,
                        "percentage": "100.00%"
                    }
                ]
            }
        ]
    ],
    "client_001": [
        [
            1,
            {
                "accuracy": 0.998395,
                "precision": 0.9985716791540331,
                "recall": 0.9998193550976988,
                "f1": 0.9991951276387151,
                "mcc": 0.7438407562785343,
                "missrate": 0.00018064490230121534,
                "fallout": 0.39915966386554624,
                "loss": 0.015136796981096268
            }
        ],
        [
            2,
            {
                "accuracy": 0.9987,
                "precision": 0.9991072413758514,
                "recall": 0.9995885310558694,
                "f1": 0.9993478282681328,
                "mcc": 0.8062667672869933,
                "missrate": 0.00041146894413054605,
                "fallout": 0.24929971988795518,
                "loss": 0.014163291081786156
            }
        ],
        [
            3,
            {
                "accuracy": 0.99876,
                "precision": 0.9993376885329801,
                "recall": 0.9994179219814738,
                "f1": 0.9993778036468735,
                "mcc": 0.8237937553388794,
                "missrate": 0.0005820780185261383,
                "fallout": 0.18487394957983194,
                "loss": 0.010883311741054058
            }
        ],
        [
            4,
            {
                "accuracy": 0.99869,
                "precision": 0.9993326308394802,
                "recall": 0.9993526891000873,
                "f1": 0.9993426598691342,
                "mcc": 0.8153571408161199,
                "missrate": 0.0006473108999126883,
                "fallout": 0.18627450980392157,
                "loss": 0.008461486548185349
            }
        ],
        [
            5,
            {
                "accuracy": 0.99869,
                "precision": 0.9992925451316067,
                "recall": 0.9993928324117098,
                "f1": 0.9993426862556198,
                "mcc": 0.8133459127414695,
                "missrate": 0.000607167588290196,
                "fallout": 0.19747899159663865,
                "loss": 0.0076281181536614895
            }
        ],
        [
            6,
            {
                "accuracy": 0.998665,
                "precision": 0.9993025484578293,
                "recall": 0.9993577070140401,
                "f1": 0.9993301269748083,
                "mcc": 0.81092852345053,
                "missrate": 0.0006422929859598767,
                "fallout": 0.19467787114845939,
                "loss": 0.0089602991938591
            }
        ],
        [
            7,
            {
                "accuracy": 0.99865,
                "precision": 0.9993025379589953,
                "recall": 0.9993426532721816,
                "f1": 0.9993225952130061,
                "mcc": 0.8091947052973801,
                "missrate": 0.0006573467278183113,
                "fallout": 0.19467787114845939,
                "loss": 0.008232737891376019
            }
        ],
        [
            8,
            {
                "accuracy": 0.99871,
                "precision": 0.9993376552997612,
                "recall": 0.9993677428419457,
                "f1": 0.9993526988443918,
                "mcc": 0.8179254442632327,
                "missrate": 0.0006322571580542537,
                "fallout": 0.18487394957983194,
                "loss": 0.008197701536118984
            }
        ],
        [
            9,
            {
                "accuracy": 0.998805,
                "precision": 0.9993377184400258,
                "recall": 0.9994630832070491,
                "f1": 0.999400396892099,
                "mcc": 0.8291839142701373,
                "missrate": 0.0005369167929508345,
                "fallout": 0.18487394957983194,
                "loss": 0.007919574156403542
            }
        ],
        [
            10,
            {
                "accuracy": 0.99878,
                "precision": 0.9993377018253339,
                "recall": 0.9994379936372851,
                "f1": 0.9993878452151573,
                "mcc": 0.826176457095315,
                "missrate": 0.0005620063627148922,
                "fallout": 0.18487394957983194,
                "loss": 0.00890086404979229,
                "attack_stats": [
                    {
                        "attack": "DDoS",
                        "count": 97025,
                        "correct": 97001,
                        "missed": 24,
                        "percentage": "99.98%"
                    },
                    {
                        "attack": "DoS",
                        "count": 88458,
                        "correct": 88438,
                        "missed": 20,
                        "percentage": "99.98%"
                    },
                    {
                        "attack": "Reconnaissance",
                        "count": 13794,
                        "correct": 13726,
                        "missed": 68,
                        "percentage": "99.51%"
                    },
                    {
                        "attack": "Theft",
                        "count": 9,
                        "correct": 9,
                        "missed": 0,
                        "percentage": "100.00%"
                    }
                ]
            }
        ]
    ],
    "client_002": [
        [
            1,
            {
                "accuracy": 0.998395,
                "precision": 0.9985716791540331,
                "recall": 0.9998193550976988,
                "f1": 0.9991951276387151,
                "mcc": 0.7438407562785343,
                "missrate": 0.00018064490230121534,
                "fallout": 0.39915966386554624,
                "loss": 0.015136796981096268
            }
        ],
        [
            2,
            {
                "accuracy": 0.9987,
                "precision": 0.9991072413758514,
                "recall": 0.9995885310558694,
                "f1": 0.9993478282681328,
                "mcc": 0.8062667672869933,
                "missrate": 0.00041146894413054605,
                "fallout": 0.24929971988795518,
                "loss": 0.014163291081786156
            }
        ],
        [
            3,
            {
                "accuracy": 0.99876,
                "precision": 0.9993376885329801,
                "recall": 0.9994179219814738,
                "f1": 0.9993778036468735,
                "mcc": 0.8237937553388794,
                "missrate": 0.0005820780185261383,
                "fallout": 0.18487394957983194,
                "loss": 0.010883311741054058
            }
        ],
        [
            4,
            {
                "accuracy": 0.99869,
                "precision": 0.9993326308394802,
                "recall": 0.9993526891000873,
                "f1": 0.9993426598691342,
                "mcc": 0.8153571408161199,
                "missrate": 0.0006473108999126883,
                "fallout": 0.18627450980392157,
                "loss": 0.008461486548185349
            }
        ],
        [
            5,
            {
                "accuracy": 0.99869,
                "precision": 0.9992925451316067,
                "recall": 0.9993928324117098,
                "f1": 0.9993426862556198,
                "mcc": 0.8133459127414695,
                "missrate": 0.000607167588290196,
                "fallout": 0.19747899159663865,
                "loss": 0.0076281181536614895
            }
        ],
        [
            6,
            {
                "accuracy": 0.998665,
                "precision": 0.9993025484578293,
                "recall": 0.9993577070140401,
                "f1": 0.9993301269748083,
                "mcc": 0.81092852345053,
                "missrate": 0.0006422929859598767,
                "fallout": 0.19467787114845939,
                "loss": 0.0089602991938591
            }
        ],
        [
            7,
            {
                "accuracy": 0.99865,
                "precision": 0.9993025379589953,
                "recall": 0.9993426532721816,
                "f1": 0.9993225952130061,
                "mcc": 0.8091947052973801,
                "missrate": 0.0006573467278183113,
                "fallout": 0.19467787114845939,
                "loss": 0.008232737891376019
            }
        ],
        [
            8,
            {
                "accuracy": 0.99871,
                "precision": 0.9993376552997612,
                "recall": 0.9993677428419457,
                "f1": 0.9993526988443918,
                "mcc": 0.8179254442632327,
                "missrate": 0.0006322571580542537,
                "fallout": 0.18487394957983194,
                "loss": 0.008197701536118984
            }
        ],
        [
            9,
            {
                "accuracy": 0.998805,
                "precision": 0.9993377184400258,
                "recall": 0.9994630832070491,
                "f1": 0.999400396892099,
                "mcc": 0.8291839142701373,
                "missrate": 0.0005369167929508345,
                "fallout": 0.18487394957983194,
                "loss": 0.007919574156403542
            }
        ],
        [
            10,
            {
                "accuracy": 0.99878,
                "precision": 0.9993377018253339,
                "recall": 0.9994379936372851,
                "f1": 0.9993878452151573,
                "mcc": 0.826176457095315,
                "missrate": 0.0005620063627148922,
                "fallout": 0.18487394957983194,
                "loss": 0.00890086404979229,
                "attack_stats": [
                    {
                        "attack": "DDoS",
                        "count": 97025,
                        "correct": 97001,
                        "missed": 24,
                        "percentage": "99.98%"
                    },
                    {
                        "attack": "DoS",
                        "count": 88458,
                        "correct": 88438,
                        "missed": 20,
                        "percentage": "99.98%"
                    },
                    {
                        "attack": "Reconnaissance",
                        "count": 13794,
                        "correct": 13726,
                        "missed": 68,
                        "percentage": "99.51%"
                    },
                    {
                        "attack": "Theft",
                        "count": 9,
                        "correct": 9,
                        "missed": 0,
                        "percentage": "100.00%"
                    }
                ]
            }
        ]
    ],
    "client_003": [
        [
            1,
            {
                "accuracy": 0.998395,
                "precision": 0.9985716791540331,
                "recall": 0.9998193550976988,
                "f1": 0.9991951276387151,
                "mcc": 0.7438407562785343,
                "missrate": 0.00018064490230121534,
                "fallout": 0.39915966386554624,
                "loss": 0.015136796981096268
            }
        ],
        [
            2,
            {
                "accuracy": 0.9987,
                "precision": 0.9991072413758514,
                "recall": 0.9995885310558694,
                "f1": 0.9993478282681328,
                "mcc": 0.8062667672869933,
                "missrate": 0.00041146894413054605,
                "fallout": 0.24929971988795518,
                "loss": 0.014163291081786156
            }
        ],
        [
            3,
            {
                "accuracy": 0.99876,
                "precision": 0.9993376885329801,
                "recall": 0.9994179219814738,
                "f1": 0.9993778036468735,
                "mcc": 0.8237937553388794,
                "missrate": 0.0005820780185261383,
                "fallout": 0.18487394957983194,
                "loss": 0.010883311741054058
            }
        ],
        [
            4,
            {
                "accuracy": 0.99869,
                "precision": 0.9993326308394802,
                "recall": 0.9993526891000873,
                "f1": 0.9993426598691342,
                "mcc": 0.8153571408161199,
                "missrate": 0.0006473108999126883,
                "fallout": 0.18627450980392157,
                "loss": 0.008461486548185349
            }
        ],
        [
            5,
            {
                "accuracy": 0.99869,
                "precision": 0.9992925451316067,
                "recall": 0.9993928324117098,
                "f1": 0.9993426862556198,
                "mcc": 0.8133459127414695,
                "missrate": 0.000607167588290196,
                "fallout": 0.19747899159663865,
                "loss": 0.0076281181536614895
            }
        ],
        [
            6,
            {
                "accuracy": 0.998665,
                "precision": 0.9993025484578293,
                "recall": 0.9993577070140401,
                "f1": 0.9993301269748083,
                "mcc": 0.81092852345053,
                "missrate": 0.0006422929859598767,
                "fallout": 0.19467787114845939,
                "loss": 0.0089602991938591
            }
        ],
        [
            7,
            {
                "accuracy": 0.99865,
                "precision": 0.9993025379589953,
                "recall": 0.9993426532721816,
                "f1": 0.9993225952130061,
                "mcc": 0.8091947052973801,
                "missrate": 0.0006573467278183113,
                "fallout": 0.19467787114845939,
                "loss": 0.008232737891376019
            }
        ],
        [
            8,
            {
                "accuracy": 0.99871,
                "precision": 0.9993376552997612,
                "recall": 0.9993677428419457,
                "f1": 0.9993526988443918,
                "mcc": 0.8179254442632327,
                "missrate": 0.0006322571580542537,
                "fallout": 0.18487394957983194,
                "loss": 0.008197701536118984
            }
        ],
        [
            9,
            {
                "accuracy": 0.998805,
                "precision": 0.9993377184400258,
                "recall": 0.9994630832070491,
                "f1": 0.999400396892099,
                "mcc": 0.8291839142701373,
                "missrate": 0.0005369167929508345,
                "fallout": 0.18487394957983194,
                "loss": 0.007919574156403542
            }
        ],
        [
            10,
            {
                "accuracy": 0.99878,
                "precision": 0.9993377018253339,
                "recall": 0.9994379936372851,
                "f1": 0.9993878452151573,
                "mcc": 0.826176457095315,
                "missrate": 0.0005620063627148922,
                "fallout": 0.18487394957983194,
                "loss": 0.00890086404979229,
                "attack_stats": [
                    {
                        "attack": "DDoS",
                        "count": 97025,
                        "correct": 97001,
                        "missed": 24,
                        "percentage": "99.98%"
                    },
                    {
                        "attack": "DoS",
                        "count": 88458,
                        "correct": 88438,
                        "missed": 20,
                        "percentage": "99.98%"
                    },
                    {
                        "attack": "Reconnaissance",
                        "count": 13794,
                        "correct": 13726,
                        "missed": 68,
                        "percentage": "99.51%"
                    },
                    {
                        "attack": "Theft",
                        "count": 9,
                        "correct": 9,
                        "missed": 0,
                        "percentage": "100.00%"
                    }
                ]
            }
        ]
    ]
}