{
    "attacker_000": [
        [
            1,
            {
                "accuracy": 0.99325,
                "precision": 0.9989010545843163,
                "recall": 0.9943197214054174,
                "f1": 0.9966051229951365,
                "mcc": 0.457338559163973,
                "missrate": 0.00568027859458266,
                "fallout": 0.30532212885154064,
                "loss": 0.04124722629785538
            }
        ],
        [
            2,
            {
                "accuracy": 0.99303,
                "precision": 0.9993187392133709,
                "recall": 0.9936824463334103,
                "f1": 0.9964926229343211,
                "mcc": 0.5029076782645169,
                "missrate": 0.006317553666589725,
                "fallout": 0.18907563025210083,
                "loss": 0.03893253579735756
            }
        ],
        [
            3,
            {
                "accuracy": 0.99353,
                "precision": 0.9993694575317037,
                "recall": 0.9941340585891633,
                "f1": 0.9967448833792839,
                "mcc": 0.5233570569497965,
                "missrate": 0.005865941410836687,
                "fallout": 0.17507002801120447,
                "loss": 0.038257308304309845
            }
        ],
        [
            4,
            {
                "accuracy": 0.96176,
                "precision": 0.9993537829753083,
                "recall": 0.962245215419046,
                "f1": 0.9804484983587782,
                "mcc": 0.23839205139182715,
                "missrate": 0.03775478458095401,
                "fallout": 0.17366946778711484,
                "loss": 0.04209444299340248
            }
        ],
        [
            5,
            {
                "accuracy": 0.961845,
                "precision": 0.9999165305941456,
                "recall": 0.9617885852493402,
                "f1": 0.9804820281707433,
                "mcc": 0.28070711139510285,
                "missrate": 0.03821141475065985,
                "fallout": 0.022408963585434174,
                "loss": 0.05060682073235512
            }
        ],
        [
            6,
            {
                "accuracy": 0.96236,
                "precision": 0.9999165754210334,
                "recall": 0.9623054303864798,
                "f1": 0.9807505446511675,
                "mcc": 0.28254196413508664,
                "missrate": 0.037694569613520267,
                "fallout": 0.022408963585434174,
                "loss": 0.04956098273396492
            }
        ],
        [
            7,
            {
                "accuracy": 0.96225,
                "precision": 0.9999687089304713,
                "recall": 0.9621448571399898,
                "f1": 0.9806922160221361,
                "mcc": 0.286004685773419,
                "missrate": 0.03785514286001024,
                "fallout": 0.008403361344537815,
                "loss": 0.059573929756879807
            }
        ],
        [
            8,
            {
                "accuracy": 0.958775,
                "precision": 0.9999685951018827,
                "recall": 0.9586574069427858,
                "f1": 0.9788773348294688,
                "mcc": 0.274164726643271,
                "missrate": 0.04134259305721426,
                "fallout": 0.008403361344537815,
                "loss": 0.07175592333078384
            }
        ],
        [
            9,
            {
                "accuracy": 0.96256,
                "precision": 0.9999687190448882,
                "recall": 0.962455967805064,
                "f1": 0.9808538057152207,
                "mcc": 0.2871324322647864,
                "missrate": 0.03754403219493592,
                "fallout": 0.008403361344537815,
                "loss": 0.07219914346933365
            }
        ],
        [
            10,
            {
                "accuracy": 0.9588,
                "precision": 0.9999790635108399,
                "recall": 0.9586724606846442,
                "f1": 0.9788901982886714,
                "mcc": 0.2749918902252674,
                "missrate": 0.04132753931535582,
                "fallout": 0.0056022408963585435,
                "loss": 0.06474209576845169,
                "attack_stats": [
                    {
                        "attack": "DDoS",
                        "count": 97025,
                        "correct": 97002,
                        "missed": 23,
                        "percentage": "99.98%"
                    },
                    {
                        "attack": "DoS",
                        "count": 88458,
                        "correct": 88439,
                        "missed": 19,
                        "percentage": "99.98%"
                    },
                    {
                        "attack": "Reconnaissance",
                        "count": 13794,
                        "correct": 5605,
                        "missed": 8189,
                        "percentage": "40.63%"
                    },
                    {
                        "attack": "Theft",
                        "count": 9,
                        "correct": 4,
                        "missed": 5,
                        "percentage": "44.44%"
                    }
                ]
            }
        ]
    ],
    "attacker_001": [
        [
            1,
            {
                "accuracy": 0.99325,
                "precision": 0.9989010545843163,
                "recall": 0.9943197214054174,
                "f1": 0.9966051229951365,
                "mcc": 0.457338559163973,
                "missrate": 0.00568027859458266,
                "fallout": 0.30532212885154064,
                "loss": 0.04124722629785538
            }
        ],
        [
            2,
            {
                "accuracy": 0.99303,
                "precision": 0.9993187392133709,
                "recall": 0.9936824463334103,
                "f1": 0.9964926229343211,
                "mcc": 0.5029076782645169,
                "missrate": 0.006317553666589725,
                "fallout": 0.18907563025210083,
                "loss": 0.03893253579735756
            }
        ],
        [
            3,
            {
                "accuracy": 0.99353,
                "precision": 0.9993694575317037,
                "recall": 0.9941340585891633,
                "f1": 0.9967448833792839,
                "mcc": 0.5233570569497965,
                "missrate": 0.005865941410836687,
                "fallout": 0.17507002801120447,
                "loss": 0.038257308304309845
            }
        ],
        [
            4,
            {
                "accuracy": 0.96176,
                "precision": 0.9993537829753083,
                "recall": 0.962245215419046,
                "f1": 0.9804484983587782,
                "mcc": 0.23839205139182715,
                "missrate": 0.03775478458095401,
                "fallout": 0.17366946778711484,
                "loss": 0.04209444299340248
            }
        ],
        [
            5,
            {
                "accuracy": 0.961845,
                "precision": 0.9999165305941456,
                "recall": 0.9617885852493402,
                "f1": 0.9804820281707433,
                "mcc": 0.28070711139510285,
                "missrate": 0.03821141475065985,
                "fallout": 0.022408963585434174,
                "loss": 0.05060682073235512
            }
        ],
        [
            6,
            {
                "accuracy": 0.96236,
                "precision": 0.9999165754210334,
                "recall": 0.9623054303864798,
                "f1": 0.9807505446511675,
                "mcc": 0.28254196413508664,
                "missrate": 0.037694569613520267,
                "fallout": 0.022408963585434174,
                "loss": 0.04956098273396492
            }
        ],
        [
            7,
            {
                "accuracy": 0.96225,
                "precision": 0.9999687089304713,
                "recall": 0.9621448571399898,
                "f1": 0.9806922160221361,
                "mcc": 0.286004685773419,
                "missrate": 0.03785514286001024,
                "fallout": 0.008403361344537815,
                "loss": 0.059573929756879807
            }
        ],
        [
            8,
            {
                "accuracy": 0.958775,
                "precision": 0.9999685951018827,
                "recall": 0.9586574069427858,
                "f1": 0.9788773348294688,
                "mcc": 0.274164726643271,
                "missrate": 0.04134259305721426,
                "fallout": 0.008403361344537815,
                "loss": 0.07175592333078384
            }
        ],
        [
            9,
            {
                "accuracy": 0.96256,
                "precision": 0.9999687190448882,
                "recall": 0.962455967805064,
                "f1": 0.9808538057152207,
                "mcc": 0.2871324322647864,
                "missrate": 0.03754403219493592,
                "fallout": 0.008403361344537815,
                "loss": 0.07219914346933365
            }
        ],
        [
            10,
            {
                "accuracy": 0.9588,
                "precision": 0.9999790635108399,
                "recall": 0.9586724606846442,
                "f1": 0.9788901982886714,
                "mcc": 0.2749918902252674,
                "missrate": 0.04132753931535582,
                "fallout": 0.0056022408963585435,
                "loss": 0.06474209576845169,
                "attack_stats": [
                    {
                        "attack": "DDoS",
                        "count": 97025,
                        "correct": 97002,
                        "missed": 23,
                        "percentage": "99.98%"
                    },
                    {
                        "attack": "DoS",
                        "count": 88458,
                        "correct": 88439,
                        "missed": 19,
                        "percentage": "99.98%"
                    },
                    {
                        "attack": "Reconnaissance",
                        "count": 13794,
                        "correct": 5605,
                        "missed": 8189,
                        "percentage": "40.63%"
                    },
                    {
                        "attack": "Theft",
                        "count": 9,
                        "correct": 4,
                        "missed": 5,
                        "percentage": "44.44%"
                    }
                ]
            }
        ]
    ],
    "attacker_002": [
        [
            1,
            {
                "accuracy": 0.99325,
                "precision": 0.9989010545843163,
                "recall": 0.9943197214054174,
                "f1": 0.9966051229951365,
                "mcc": 0.457338559163973,
                "missrate": 0.00568027859458266,
                "fallout": 0.30532212885154064,
                "loss": 0.04124722629785538
            }
        ],
        [
            2,
            {
                "accuracy": 0.99303,
                "precision": 0.9993187392133709,
                "recall": 0.9936824463334103,
                "f1": 0.9964926229343211,
                "mcc": 0.5029076782645169,
                "missrate": 0.006317553666589725,
                "fallout": 0.18907563025210083,
                "loss": 0.03893253579735756
            }
        ],
        [
            3,
            {
                "accuracy": 0.99353,
                "precision": 0.9993694575317037,
                "recall": 0.9941340585891633,
                "f1": 0.9967448833792839,
                "mcc": 0.5233570569497965,
                "missrate": 0.005865941410836687,
                "fallout": 0.17507002801120447,
                "loss": 0.038257308304309845
            }
        ],
        [
            4,
            {
                "accuracy": 0.96176,
                "precision": 0.9993537829753083,
                "recall": 0.962245215419046,
                "f1": 0.9804484983587782,
                "mcc": 0.23839205139182715,
                "missrate": 0.03775478458095401,
                "fallout": 0.17366946778711484,
                "loss": 0.04209444299340248
            }
        ],
        [
            5,
            {
                "accuracy": 0.961845,
                "precision": 0.9999165305941456,
                "recall": 0.9617885852493402,
                "f1": 0.9804820281707433,
                "mcc": 0.28070711139510285,
                "missrate": 0.03821141475065985,
                "fallout": 0.022408963585434174,
                "loss": 0.05060682073235512
            }
        ],
        [
            6,
            {
                "accuracy": 0.96236,
                "precision": 0.9999165754210334,
                "recall": 0.9623054303864798,
                "f1": 0.9807505446511675,
                "mcc": 0.28254196413508664,
                "missrate": 0.037694569613520267,
                "fallout": 0.022408963585434174,
                "loss": 0.04956098273396492
            }
        ],
        [
            7,
            {
                "accuracy": 0.96225,
                "precision": 0.9999687089304713,
                "recall": 0.9621448571399898,
                "f1": 0.9806922160221361,
                "mcc": 0.286004685773419,
                "missrate": 0.03785514286001024,
                "fallout": 0.008403361344537815,
                "loss": 0.059573929756879807
            }
        ],
        [
            8,
            {
                "accuracy": 0.958775,
                "precision": 0.9999685951018827,
                "recall": 0.9586574069427858,
                "f1": 0.9788773348294688,
                "mcc": 0.274164726643271,
                "missrate": 0.04134259305721426,
                "fallout": 0.008403361344537815,
                "loss": 0.07175592333078384
            }
        ],
        [
            9,
            {
                "accuracy": 0.96256,
                "precision": 0.9999687190448882,
                "recall": 0.962455967805064,
                "f1": 0.9808538057152207,
                "mcc": 0.2871324322647864,
                "missrate": 0.03754403219493592,
                "fallout": 0.008403361344537815,
                "loss": 0.07219914346933365
            }
        ],
        [
            10,
            {
                "accuracy": 0.9588,
                "precision": 0.9999790635108399,
                "recall": 0.9586724606846442,
                "f1": 0.9788901982886714,
                "mcc": 0.2749918902252674,
                "missrate": 0.04132753931535582,
                "fallout": 0.0056022408963585435,
                "loss": 0.06474209576845169,
                "attack_stats": [
                    {
                        "attack": "DDoS",
                        "count": 97025,
                        "correct": 97002,
                        "missed": 23,
                        "percentage": "99.98%"
                    },
                    {
                        "attack": "DoS",
                        "count": 88458,
                        "correct": 88439,
                        "missed": 19,
                        "percentage": "99.98%"
                    },
                    {
                        "attack": "Reconnaissance",
                        "count": 13794,
                        "correct": 5605,
                        "missed": 8189,
                        "percentage": "40.63%"
                    },
                    {
                        "attack": "Theft",
                        "count": 9,
                        "correct": 4,
                        "missed": 5,
                        "percentage": "44.44%"
                    }
                ]
            }
        ]
    ],
    "client_000": [
        [
            1,
            {
                "accuracy": 0.99325,
                "precision": 0.9989010545843163,
                "recall": 0.9943197214054174,
                "f1": 0.9966051229951365,
                "mcc": 0.457338559163973,
                "missrate": 0.00568027859458266,
                "fallout": 0.30532212885154064,
                "loss": 0.04124722629785538
            }
        ],
        [
            2,
            {
                "accuracy": 0.99303,
                "precision": 0.9993187392133709,
                "recall": 0.9936824463334103,
                "f1": 0.9964926229343211,
                "mcc": 0.5029076782645169,
                "missrate": 0.006317553666589725,
                "fallout": 0.18907563025210083,
                "loss": 0.03893253579735756
            }
        ],
        [
            3,
            {
                "accuracy": 0.99353,
                "precision": 0.9993694575317037,
                "recall": 0.9941340585891633,
                "f1": 0.9967448833792839,
                "mcc": 0.5233570569497965,
                "missrate": 0.005865941410836687,
                "fallout": 0.17507002801120447,
                "loss": 0.038257308304309845
            }
        ],
        [
            4,
            {
                "accuracy": 0.96176,
                "precision": 0.9993537829753083,
                "recall": 0.962245215419046,
                "f1": 0.9804484983587782,
                "mcc": 0.23839205139182715,
                "missrate": 0.03775478458095401,
                "fallout": 0.17366946778711484,
                "loss": 0.04209444299340248
            }
        ],
        [
            5,
            {
                "accuracy": 0.961845,
                "precision": 0.9999165305941456,
                "recall": 0.9617885852493402,
                "f1": 0.9804820281707433,
                "mcc": 0.28070711139510285,
                "missrate": 0.03821141475065985,
                "fallout": 0.022408963585434174,
                "loss": 0.05060682073235512
            }
        ],
        [
            6,
            {
                "accuracy": 0.96236,
                "precision": 0.9999165754210334,
                "recall": 0.9623054303864798,
                "f1": 0.9807505446511675,
                "mcc": 0.28254196413508664,
                "missrate": 0.037694569613520267,
                "fallout": 0.022408963585434174,
                "loss": 0.04956098273396492
            }
        ],
        [
            7,
            {
                "accuracy": 0.96225,
                "precision": 0.9999687089304713,
                "recall": 0.9621448571399898,
                "f1": 0.9806922160221361,
                "mcc": 0.286004685773419,
                "missrate": 0.03785514286001024,
                "fallout": 0.008403361344537815,
                "loss": 0.059573929756879807
            }
        ],
        [
            8,
            {
                "accuracy": 0.958775,
                "precision": 0.9999685951018827,
                "recall": 0.9586574069427858,
                "f1": 0.9788773348294688,
                "mcc": 0.274164726643271,
                "missrate": 0.04134259305721426,
                "fallout": 0.008403361344537815,
                "loss": 0.07175592333078384
            }
        ],
        [
            9,
            {
                "accuracy": 0.96256,
                "precision": 0.9999687190448882,
                "recall": 0.962455967805064,
                "f1": 0.9808538057152207,
                "mcc": 0.2871324322647864,
                "missrate": 0.03754403219493592,
                "fallout": 0.008403361344537815,
                "loss": 0.07219914346933365
            }
        ],
        [
            10,
            {
                "accuracy": 0.9588,
                "precision": 0.9999790635108399,
                "recall": 0.9586724606846442,
                "f1": 0.9788901982886714,
                "mcc": 0.2749918902252674,
                "missrate": 0.04132753931535582,
                "fallout": 0.0056022408963585435,
                "loss": 0.06474209576845169,
                "attack_stats": [
                    {
                        "attack": "DDoS",
                        "count": 97025,
                        "correct": 97002,
                        "missed": 23,
                        "percentage": "99.98%"
                    },
                    {
                        "attack": "DoS",
                        "count": 88458,
                        "correct": 88439,
                        "missed": 19,
                        "percentage": "99.98%"
                    },
                    {
                        "attack": "Reconnaissance",
                        "count": 13794,
                        "correct": 5605,
                        "missed": 8189,
                        "percentage": "40.63%"
                    },
                    {
                        "attack": "Theft",
                        "count": 9,
                        "correct": 4,
                        "missed": 5,
                        "percentage": "44.44%"
                    }
                ]
            }
        ]
    ],
    "client_001": [
        [
            1,
            {
                "accuracy": 0.99325,
                "precision": 0.9989010545843163,
                "recall": 0.9943197214054174,
                "f1": 0.9966051229951365,
                "mcc": 0.457338559163973,
                "missrate": 0.00568027859458266,
                "fallout": 0.30532212885154064,
                "loss": 0.04124722629785538
            }
        ],
        [
            2,
            {
                "accuracy": 0.99303,
                "precision": 0.9993187392133709,
                "recall": 0.9936824463334103,
                "f1": 0.9964926229343211,
                "mcc": 0.5029076782645169,
                "missrate": 0.006317553666589725,
                "fallout": 0.18907563025210083,
                "loss": 0.03893253579735756
            }
        ],
        [
            3,
            {
                "accuracy": 0.99353,
                "precision": 0.9993694575317037,
                "recall": 0.9941340585891633,
                "f1": 0.9967448833792839,
                "mcc": 0.5233570569497965,
                "missrate": 0.005865941410836687,
                "fallout": 0.17507002801120447,
                "loss": 0.038257308304309845
            }
        ],
        [
            4,
            {
                "accuracy": 0.96176,
                "precision": 0.9993537829753083,
                "recall": 0.962245215419046,
                "f1": 0.9804484983587782,
                "mcc": 0.23839205139182715,
                "missrate": 0.03775478458095401,
                "fallout": 0.17366946778711484,
                "loss": 0.04209444299340248
            }
        ],
        [
            5,
            {
                "accuracy": 0.961845,
                "precision": 0.9999165305941456,
                "recall": 0.9617885852493402,
                "f1": 0.9804820281707433,
                "mcc": 0.28070711139510285,
                "missrate": 0.03821141475065985,
                "fallout": 0.022408963585434174,
                "loss": 0.05060682073235512
            }
        ],
        [
            6,
            {
                "accuracy": 0.96236,
                "precision": 0.9999165754210334,
                "recall": 0.9623054303864798,
                "f1": 0.9807505446511675,
                "mcc": 0.28254196413508664,
                "missrate": 0.037694569613520267,
                "fallout": 0.022408963585434174,
                "loss": 0.04956098273396492
            }
        ],
        [
            7,
            {
                "accuracy": 0.96225,
                "precision": 0.9999687089304713,
                "recall": 0.9621448571399898,
                "f1": 0.9806922160221361,
                "mcc": 0.286004685773419,
                "missrate": 0.03785514286001024,
                "fallout": 0.008403361344537815,
                "loss": 0.059573929756879807
            }
        ],
        [
            8,
            {
                "accuracy": 0.958775,
                "precision": 0.9999685951018827,
                "recall": 0.9586574069427858,
                "f1": 0.9788773348294688,
                "mcc": 0.274164726643271,
                "missrate": 0.04134259305721426,
                "fallout": 0.008403361344537815,
                "loss": 0.07175592333078384
            }
        ],
        [
            9,
            {
                "accuracy": 0.96256,
                "precision": 0.9999687190448882,
                "recall": 0.962455967805064,
                "f1": 0.9808538057152207,
                "mcc": 0.2871324322647864,
                "missrate": 0.03754403219493592,
                "fallout": 0.008403361344537815,
                "loss": 0.07219914346933365
            }
        ],
        [
            10,
            {
                "accuracy": 0.9588,
                "precision": 0.9999790635108399,
                "recall": 0.9586724606846442,
                "f1": 0.9788901982886714,
                "mcc": 0.2749918902252674,
                "missrate": 0.04132753931535582,
                "fallout": 0.0056022408963585435,
                "loss": 0.06474209576845169,
                "attack_stats": [
                    {
                        "attack": "DDoS",
                        "count": 97025,
                        "correct": 97002,
                        "missed": 23,
                        "percentage": "99.98%"
                    },
                    {
                        "attack": "DoS",
                        "count": 88458,
                        "correct": 88439,
                        "missed": 19,
                        "percentage": "99.98%"
                    },
                    {
                        "attack": "Reconnaissance",
                        "count": 13794,
                        "correct": 5605,
                        "missed": 8189,
                        "percentage": "40.63%"
                    },
                    {
                        "attack": "Theft",
                        "count": 9,
                        "correct": 4,
                        "missed": 5,
                        "percentage": "44.44%"
                    }
                ]
            }
        ]
    ]
}