{
    "attacker_000": [
        [
            1,
            {
                "accuracy": 0.99828,
                "precision": 0.9984615847180741,
                "recall": 0.999814337183746,
                "f1": 0.9991375030713916,
                "mcc": 0.7221349124959222,
                "missrate": 0.00018566281625402687,
                "fallout": 0.42997198879551823,
                "loss": 0.02407769486308098
            }
        ],
        [
            2,
            {
                "accuracy": 0.998545,
                "precision": 0.9988318518407107,
                "recall": 0.9997089609907369,
                "f1": 0.9992702139451831,
                "mcc": 0.7746817453322431,
                "missrate": 0.00029103900926306914,
                "fallout": 0.32633053221288516,
                "loss": 0.01330247800797224
            }
        ],
        [
            3,
            {
                "accuracy": 0.998775,
                "precision": 0.9991623824451411,
                "recall": 0.9996086027116807,
                "f1": 0.9993854427696715,
                "mcc": 0.8182373929812343,
                "missrate": 0.0003913972883192999,
                "fallout": 0.2338935574229692,
                "loss": 0.011418169364333153
            }
        ],
        [
            4,
            {
                "accuracy": 0.99881,
                "precision": 0.9992225042386059,
                "recall": 0.9995835131419166,
                "f1": 0.9994029760889416,
                "mcc": 0.8250602340230605,
                "missrate": 0.0004164868580833576,
                "fallout": 0.21708683473389356,
                "loss": 0.009203287772834301
            }
        ],
        [
            5,
            {
                "accuracy": 0.998865,
                "precision": 0.9992826506809802,
                "recall": 0.9995784952279638,
                "f1": 0.9994305510610063,
                "mcc": 0.834397726222225,
                "missrate": 0.0004215047720361691,
                "fallout": 0.20028011204481794,
                "loss": 0.007162794936448336
            }
        ],
        [
            6,
            {
                "accuracy": 0.99886,
                "precision": 0.9992826470824304,
                "recall": 0.999573477314011,
                "f1": 0.9994280410405638,
                "mcc": 0.8337583667699395,
                "missrate": 0.00042652268598898066,
                "fallout": 0.20028011204481794,
                "loss": 0.006768637802451849
            }
        ],
        [
            7,
            {
                "accuracy": 0.99888,
                "precision": 0.9992826614764131,
                "recall": 0.9995935489698222,
                "f1": 0.9994380810467748,
                "mcc": 0.8363246076827714,
                "missrate": 0.0004064510301777345,
                "fallout": 0.20028011204481794,
                "loss": 0.006283704191446304
            }
        ],
        [
            8,
            {
                "accuracy": 0.998875,
                "precision": 0.9992826578779715,
                "recall": 0.9995885310558694,
                "f1": 0.9994355710641116,
                "mcc": 0.8356808410648061,
                "missrate": 0.00041146894413054605,
                "fallout": 0.20028011204481794,
                "loss": 0.006229654420167208
            }
        ],
        [
            9,
            {
                "accuracy": 0.998885,
                "precision": 0.9992826650748186,
                "recall": 0.9995985668837751,
                "f1": 0.999440591016845,
                "mcc": 0.8369698546339057,
                "missrate": 0.000401433116224923,
                "fallout": 0.20028011204481794,
                "loss": 0.005984542425721884
            }
        ],
        [
            10,
            {
                "accuracy": 0.998945,
                "precision": 0.9992827082528679,
                "recall": 0.9996587818512088,
                "f1": 0.9994707096754774,
                "mcc": 0.8448303861630652,
                "missrate": 0.0003412181487911845,
                "fallout": 0.20028011204481794,
                "loss": 0.005645541474223137,
                "attack_stats": [
                    {
                        "attack": "DDoS",
                        "count": 97025,
                        "correct": 97001,
                        "missed": 24,
                        "percentage": "99.98%"
                    },
                    {
                        "attack": "DoS",
                        "count": 88458,
                        "correct": 88437,
                        "missed": 21,
                        "percentage": "99.98%"
                    },
                    {
                        "attack": "Reconnaissance",
                        "count": 13794,
                        "correct": 13772,
                        "missed": 22,
                        "percentage": "99.84%"
                    },
                    {
                        "attack": "Theft",
                        "count": 9,
                        "correct": 8,
                        "missed": 1,
                        "percentage": "88.89%"
                    }
                ]
            }
        ]
    ],
    "attacker_001": [
        [
            1,
            {
                "accuracy": 0.99828,
                "precision": 0.9984615847180741,
                "recall": 0.999814337183746,
                "f1": 0.9991375030713916,
                "mcc": 0.7221349124959222,
                "missrate": 0.00018566281625402687,
                "fallout": 0.42997198879551823,
                "loss": 0.02407769486308098
            }
        ],
        [
            2,
            {
                "accuracy": 0.998545,
                "precision": 0.9988318518407107,
                "recall": 0.9997089609907369,
                "f1": 0.9992702139451831,
                "mcc": 0.7746817453322431,
                "missrate": 0.00029103900926306914,
                "fallout": 0.32633053221288516,
                "loss": 0.01330247800797224
            }
        ],
        [
            3,
            {
                "accuracy": 0.998775,
                "precision": 0.9991623824451411,
                "recall": 0.9996086027116807,
                "f1": 0.9993854427696715,
                "mcc": 0.8182373929812343,
                "missrate": 0.0003913972883192999,
                "fallout": 0.2338935574229692,
                "loss": 0.011418169364333153
            }
        ],
        [
            4,
            {
                "accuracy": 0.99881,
                "precision": 0.9992225042386059,
                "recall": 0.9995835131419166,
                "f1": 0.9994029760889416,
                "mcc": 0.8250602340230605,
                "missrate": 0.0004164868580833576,
                "fallout": 0.21708683473389356,
                "loss": 0.009203287772834301
            }
        ],
        [
            5,
            {
                "accuracy": 0.998865,
                "precision": 0.9992826506809802,
                "recall": 0.9995784952279638,
                "f1": 0.9994305510610063,
                "mcc": 0.834397726222225,
                "missrate": 0.0004215047720361691,
                "fallout": 0.20028011204481794,
                "loss": 0.007162794936448336
            }
        ],
        [
            6,
            {
                "accuracy": 0.99886,
                "precision": 0.9992826470824304,
                "recall": 0.999573477314011,
                "f1": 0.9994280410405638,
                "mcc": 0.8337583667699395,
                "missrate": 0.00042652268598898066,
                "fallout": 0.20028011204481794,
                "loss": 0.006768637802451849
            }
        ],
        [
            7,
            {
                "accuracy": 0.99888,
                "precision": 0.9992826614764131,
                "recall": 0.9995935489698222,
                "f1": 0.9994380810467748,
                "mcc": 0.8363246076827714,
                "missrate": 0.0004064510301777345,
                "fallout": 0.20028011204481794,
                "loss": 0.006283704191446304
            }
        ],
        [
            8,
            {
                "accuracy": 0.998875,
                "precision": 0.9992826578779715,
                "recall": 0.9995885310558694,
                "f1": 0.9994355710641116,
                "mcc": 0.8356808410648061,
                "missrate": 0.00041146894413054605,
                "fallout": 0.20028011204481794,
                "loss": 0.006229654420167208
            }
        ],
        [
            9,
            {
                "accuracy": 0.998885,
                "precision": 0.9992826650748186,
                "recall": 0.9995985668837751,
                "f1": 0.999440591016845,
                "mcc": 0.8369698546339057,
                "missrate": 0.000401433116224923,
                "fallout": 0.20028011204481794,
                "loss": 0.005984542425721884
            }
        ],
        [
            10,
            {
                "accuracy": 0.998945,
                "precision": 0.9992827082528679,
                "recall": 0.9996587818512088,
                "f1": 0.9994707096754774,
                "mcc": 0.8448303861630652,
                "missrate": 0.0003412181487911845,
                "fallout": 0.20028011204481794,
                "loss": 0.005645541474223137,
                "attack_stats": [
                    {
                        "attack": "DDoS",
                        "count": 97025,
                        "correct": 97001,
                        "missed": 24,
                        "percentage": "99.98%"
                    },
                    {
                        "attack": "DoS",
                        "count": 88458,
                        "correct": 88437,
                        "missed": 21,
                        "percentage": "99.98%"
                    },
                    {
                        "attack": "Reconnaissance",
                        "count": 13794,
                        "correct": 13772,
                        "missed": 22,
                        "percentage": "99.84%"
                    },
                    {
                        "attack": "Theft",
                        "count": 9,
                        "correct": 8,
                        "missed": 1,
                        "percentage": "88.89%"
                    }
                ]
            }
        ]
    ],
    "client_000": [
        [
            1,
            {
                "accuracy": 0.99828,
                "precision": 0.9984615847180741,
                "recall": 0.999814337183746,
                "f1": 0.9991375030713916,
                "mcc": 0.7221349124959222,
                "missrate": 0.00018566281625402687,
                "fallout": 0.42997198879551823,
                "loss": 0.02407769486308098
            }
        ],
        [
            2,
            {
                "accuracy": 0.998545,
                "precision": 0.9988318518407107,
                "recall": 0.9997089609907369,
                "f1": 0.9992702139451831,
                "mcc": 0.7746817453322431,
                "missrate": 0.00029103900926306914,
                "fallout": 0.32633053221288516,
                "loss": 0.01330247800797224
            }
        ],
        [
            3,
            {
                "accuracy": 0.998775,
                "precision": 0.9991623824451411,
                "recall": 0.9996086027116807,
                "f1": 0.9993854427696715,
                "mcc": 0.8182373929812343,
                "missrate": 0.0003913972883192999,
                "fallout": 0.2338935574229692,
                "loss": 0.011418169364333153
            }
        ],
        [
            4,
            {
                "accuracy": 0.99881,
                "precision": 0.9992225042386059,
                "recall": 0.9995835131419166,
                "f1": 0.9994029760889416,
                "mcc": 0.8250602340230605,
                "missrate": 0.0004164868580833576,
                "fallout": 0.21708683473389356,
                "loss": 0.009203287772834301
            }
        ],
        [
            5,
            {
                "accuracy": 0.998865,
                "precision": 0.9992826506809802,
                "recall": 0.9995784952279638,
                "f1": 0.9994305510610063,
                "mcc": 0.834397726222225,
                "missrate": 0.0004215047720361691,
                "fallout": 0.20028011204481794,
                "loss": 0.007162794936448336
            }
        ],
        [
            6,
            {
                "accuracy": 0.99886,
                "precision": 0.9992826470824304,
                "recall": 0.999573477314011,
                "f1": 0.9994280410405638,
                "mcc": 0.8337583667699395,
                "missrate": 0.00042652268598898066,
                "fallout": 0.20028011204481794,
                "loss": 0.006768637802451849
            }
        ],
        [
            7,
            {
                "accuracy": 0.99888,
                "precision": 0.9992826614764131,
                "recall": 0.9995935489698222,
                "f1": 0.9994380810467748,
                "mcc": 0.8363246076827714,
                "missrate": 0.0004064510301777345,
                "fallout": 0.20028011204481794,
                "loss": 0.006283704191446304
            }
        ],
        [
            8,
            {
                "accuracy": 0.998875,
                "precision": 0.9992826578779715,
                "recall": 0.9995885310558694,
                "f1": 0.9994355710641116,
                "mcc": 0.8356808410648061,
                "missrate": 0.00041146894413054605,
                "fallout": 0.20028011204481794,
                "loss": 0.006229654420167208
            }
        ],
        [
            9,
            {
                "accuracy": 0.998885,
                "precision": 0.9992826650748186,
                "recall": 0.9995985668837751,
                "f1": 0.999440591016845,
                "mcc": 0.8369698546339057,
                "missrate": 0.000401433116224923,
                "fallout": 0.20028011204481794,
                "loss": 0.005984542425721884
            }
        ],
        [
            10,
            {
                "accuracy": 0.998945,
                "precision": 0.9992827082528679,
                "recall": 0.9996587818512088,
                "f1": 0.9994707096754774,
                "mcc": 0.8448303861630652,
                "missrate": 0.0003412181487911845,
                "fallout": 0.20028011204481794,
                "loss": 0.005645541474223137,
                "attack_stats": [
                    {
                        "attack": "DDoS",
                        "count": 97025,
                        "correct": 97001,
                        "missed": 24,
                        "percentage": "99.98%"
                    },
                    {
                        "attack": "DoS",
                        "count": 88458,
                        "correct": 88437,
                        "missed": 21,
                        "percentage": "99.98%"
                    },
                    {
                        "attack": "Reconnaissance",
                        "count": 13794,
                        "correct": 13772,
                        "missed": 22,
                        "percentage": "99.84%"
                    },
                    {
                        "attack": "Theft",
                        "count": 9,
                        "correct": 8,
                        "missed": 1,
                        "percentage": "88.89%"
                    }
                ]
            }
        ]
    ],
    "client_001": [
        [
            1,
            {
                "accuracy": 0.99828,
                "precision": 0.9984615847180741,
                "recall": 0.999814337183746,
                "f1": 0.9991375030713916,
                "mcc": 0.7221349124959222,
                "missrate": 0.00018566281625402687,
                "fallout": 0.42997198879551823,
                "loss": 0.02407769486308098
            }
        ],
        [
            2,
            {
                "accuracy": 0.998545,
                "precision": 0.9988318518407107,
                "recall": 0.9997089609907369,
                "f1": 0.9992702139451831,
                "mcc": 0.7746817453322431,
                "missrate": 0.00029103900926306914,
                "fallout": 0.32633053221288516,
                "loss": 0.01330247800797224
            }
        ],
        [
            3,
            {
                "accuracy": 0.998775,
                "precision": 0.9991623824451411,
                "recall": 0.9996086027116807,
                "f1": 0.9993854427696715,
                "mcc": 0.8182373929812343,
                "missrate": 0.0003913972883192999,
                "fallout": 0.2338935574229692,
                "loss": 0.011418169364333153
            }
        ],
        [
            4,
            {
                "accuracy": 0.99881,
                "precision": 0.9992225042386059,
                "recall": 0.9995835131419166,
                "f1": 0.9994029760889416,
                "mcc": 0.8250602340230605,
                "missrate": 0.0004164868580833576,
                "fallout": 0.21708683473389356,
                "loss": 0.009203287772834301
            }
        ],
        [
            5,
            {
                "accuracy": 0.998865,
                "precision": 0.9992826506809802,
                "recall": 0.9995784952279638,
                "f1": 0.9994305510610063,
                "mcc": 0.834397726222225,
                "missrate": 0.0004215047720361691,
                "fallout": 0.20028011204481794,
                "loss": 0.007162794936448336
            }
        ],
        [
            6,
            {
                "accuracy": 0.99886,
                "precision": 0.9992826470824304,
                "recall": 0.999573477314011,
                "f1": 0.9994280410405638,
                "mcc": 0.8337583667699395,
                "missrate": 0.00042652268598898066,
                "fallout": 0.20028011204481794,
                "loss": 0.006768637802451849
            }
        ],
        [
            7,
            {
                "accuracy": 0.99888,
                "precision": 0.9992826614764131,
                "recall": 0.9995935489698222,
                "f1": 0.9994380810467748,
                "mcc": 0.8363246076827714,
                "missrate": 0.0004064510301777345,
                "fallout": 0.20028011204481794,
                "loss": 0.006283704191446304
            }
        ],
        [
            8,
            {
                "accuracy": 0.998875,
                "precision": 0.9992826578779715,
                "recall": 0.9995885310558694,
                "f1": 0.9994355710641116,
                "mcc": 0.8356808410648061,
                "missrate": 0.00041146894413054605,
                "fallout": 0.20028011204481794,
                "loss": 0.006229654420167208
            }
        ],
        [
            9,
            {
                "accuracy": 0.998885,
                "precision": 0.9992826650748186,
                "recall": 0.9995985668837751,
                "f1": 0.999440591016845,
                "mcc": 0.8369698546339057,
                "missrate": 0.000401433116224923,
                "fallout": 0.20028011204481794,
                "loss": 0.005984542425721884
            }
        ],
        [
            10,
            {
                "accuracy": 0.998945,
                "precision": 0.9992827082528679,
                "recall": 0.9996587818512088,
                "f1": 0.9994707096754774,
                "mcc": 0.8448303861630652,
                "missrate": 0.0003412181487911845,
                "fallout": 0.20028011204481794,
                "loss": 0.005645541474223137,
                "attack_stats": [
                    {
                        "attack": "DDoS",
                        "count": 97025,
                        "correct": 97001,
                        "missed": 24,
                        "percentage": "99.98%"
                    },
                    {
                        "attack": "DoS",
                        "count": 88458,
                        "correct": 88437,
                        "missed": 21,
                        "percentage": "99.98%"
                    },
                    {
                        "attack": "Reconnaissance",
                        "count": 13794,
                        "correct": 13772,
                        "missed": 22,
                        "percentage": "99.84%"
                    },
                    {
                        "attack": "Theft",
                        "count": 9,
                        "correct": 8,
                        "missed": 1,
                        "percentage": "88.89%"
                    }
                ]
            }
        ]
    ],
    "client_002": [
        [
            1,
            {
                "accuracy": 0.99828,
                "precision": 0.9984615847180741,
                "recall": 0.999814337183746,
                "f1": 0.9991375030713916,
                "mcc": 0.7221349124959222,
                "missrate": 0.00018566281625402687,
                "fallout": 0.42997198879551823,
                "loss": 0.02407769486308098
            }
        ],
        [
            2,
            {
                "accuracy": 0.998545,
                "precision": 0.9988318518407107,
                "recall": 0.9997089609907369,
                "f1": 0.9992702139451831,
                "mcc": 0.7746817453322431,
                "missrate": 0.00029103900926306914,
                "fallout": 0.32633053221288516,
                "loss": 0.01330247800797224
            }
        ],
        [
            3,
            {
                "accuracy": 0.998775,
                "precision": 0.9991623824451411,
                "recall": 0.9996086027116807,
                "f1": 0.9993854427696715,
                "mcc": 0.8182373929812343,
                "missrate": 0.0003913972883192999,
                "fallout": 0.2338935574229692,
                "loss": 0.011418169364333153
            }
        ],
        [
            4,
            {
                "accuracy": 0.99881,
                "precision": 0.9992225042386059,
                "recall": 0.9995835131419166,
                "f1": 0.9994029760889416,
                "mcc": 0.8250602340230605,
                "missrate": 0.0004164868580833576,
                "fallout": 0.21708683473389356,
                "loss": 0.009203287772834301
            }
        ],
        [
            5,
            {
                "accuracy": 0.998865,
                "precision": 0.9992826506809802,
                "recall": 0.9995784952279638,
                "f1": 0.9994305510610063,
                "mcc": 0.834397726222225,
                "missrate": 0.0004215047720361691,
                "fallout": 0.20028011204481794,
                "loss": 0.007162794936448336
            }
        ],
        [
            6,
            {
                "accuracy": 0.99886,
                "precision": 0.9992826470824304,
                "recall": 0.999573477314011,
                "f1": 0.9994280410405638,
                "mcc": 0.8337583667699395,
                "missrate": 0.00042652268598898066,
                "fallout": 0.20028011204481794,
                "loss": 0.006768637802451849
            }
        ],
        [
            7,
            {
                "accuracy": 0.99888,
                "precision": 0.9992826614764131,
                "recall": 0.9995935489698222,
                "f1": 0.9994380810467748,
                "mcc": 0.8363246076827714,
                "missrate": 0.0004064510301777345,
                "fallout": 0.20028011204481794,
                "loss": 0.006283704191446304
            }
        ],
        [
            8,
            {
                "accuracy": 0.998875,
                "precision": 0.9992826578779715,
                "recall": 0.9995885310558694,
                "f1": 0.9994355710641116,
                "mcc": 0.8356808410648061,
                "missrate": 0.00041146894413054605,
                "fallout": 0.20028011204481794,
                "loss": 0.006229654420167208
            }
        ],
        [
            9,
            {
                "accuracy": 0.998885,
                "precision": 0.9992826650748186,
                "recall": 0.9995985668837751,
                "f1": 0.999440591016845,
                "mcc": 0.8369698546339057,
                "missrate": 0.000401433116224923,
                "fallout": 0.20028011204481794,
                "loss": 0.005984542425721884
            }
        ],
        [
            10,
            {
                "accuracy": 0.998945,
                "precision": 0.9992827082528679,
                "recall": 0.9996587818512088,
                "f1": 0.9994707096754774,
                "mcc": 0.8448303861630652,
                "missrate": 0.0003412181487911845,
                "fallout": 0.20028011204481794,
                "loss": 0.005645541474223137,
                "attack_stats": [
                    {
                        "attack": "DDoS",
                        "count": 97025,
                        "correct": 97001,
                        "missed": 24,
                        "percentage": "99.98%"
                    },
                    {
                        "attack": "DoS",
                        "count": 88458,
                        "correct": 88437,
                        "missed": 21,
                        "percentage": "99.98%"
                    },
                    {
                        "attack": "Reconnaissance",
                        "count": 13794,
                        "correct": 13772,
                        "missed": 22,
                        "percentage": "99.84%"
                    },
                    {
                        "attack": "Theft",
                        "count": 9,
                        "correct": 8,
                        "missed": 1,
                        "percentage": "88.89%"
                    }
                ]
            }
        ]
    ]
}